filter_pre_commit_hooks/__init__.py
filter_pre_commit_hooks/filter_pre_commit_hooks.py
filter_pre_commit_hooks-2.0.5.dist-info/METADATA
filter_pre_commit_hooks-2.0.5.dist-info/WHEEL
filter_pre_commit_hooks-2.0.5.dist-info/entry_points.txt
filter_pre_commit_hooks-2.0.5.dist-info/licenses/LICENSE
filter_pre_commit_hooks-2.0.5.dist-info/RECORD
