Metadata-Version: 2.4
Name: filter-pre-commit-hooks
Version: 2.0.5
Summary: Extract and filter pre-commit hooks.
Project-URL: Homepage, https://github.com/trallnag/filter-pre-commit-hooks
Project-URL: Documentation, https://github.com/trallnag/filter-pre-commit-hooks
Project-URL: Repository, https://github.com/trallnag/filter-pre-commit-hooks.git
Project-URL: Issues, https://github.com/trallnag/filter-pre-commit-hooks/issues
Project-URL: Changelog, https://github.com/trallnag/filter-pre-commit-hooks/blob/master/CHANGELOG.md
Author-email: Tim Schwenke <tim@trallnag.com>
License-Expression: ISC
License-File: LICENSE
Requires-Python: >=3.12
Requires-Dist: click==8.1.8
Requires-Dist: pyyaml==6.0.2
